Metadata-Version: 2.1
Name: spbasiccalculator
Version: 0.0.1
Summary: a very basic addition function
Home-page: https://github.com/saurabhpl/demo
Author: Saurabh Pratap Singh
License: MIT
Platform: UNKNOWN
License-File: LICENCE.txt
